transfx/__init__.py
transfx/math_package/__init__.py
transfx/math_package/module.py
transfx/welcome_package/__init__.py
transfx/welcome_package/module.py
transfx-0.0.4.dist-info/METADATA
transfx-0.0.4.dist-info/WHEEL
transfx-0.0.4.dist-info/licenses/LICENSE
transfx-0.0.4.dist-info/RECORD
