Metadata-Version: 2.4
Name: transfx
Version: 0.0.4
Summary: transFX is a Python package
Project-URL: Homepage, https://github.com/weisiren000/transFX
Project-URL: Bug Tracker, https://github.com/weisiren000/transFX/issues
Author-email: weisiren <cxyvsir04@gmail.com>
License-File: LICENSE
Requires-Python: >=3.12
